{
  "asOf": "2026-03-02T18:41:09.817Z",
  "intervalSec": 60,
  "source": "binance",
  "hash": "e5b69bbf",
  "logosAttempted": 150,
  "logosDownloaded": 40,
  "logosMissing": 110,
  "coins": [
    {
      "symbol": "USDCUSDT",
      "base": "USDC",
      "quote": "USDT",
      "lastPrice": 0.9998,
      "priceChangePercent": -0.02,
      "quoteVolume": 2437286908.9426,
      "rankByQuoteVolume": 1,
      "tradeCount": 527562,
      "highPrice": 1.0004,
      "lowPrice": 0.9998,
      "logoPath": "/data/logos/USDCUSDT.png"
    },
    {
      "symbol": "BTCUSDT",
      "base": "BTC",
      "quote": "USDT",
      "lastPrice": 69038.5,
      "priceChangePercent": 4.011,
      "quoteVolume": 2189168675.1688137,
      "rankByQuoteVolume": 2,
      "tradeCount": 8435167,
      "highPrice": 70096,
      "lowPrice": 65056,
      "logoPath": "/data/logos/BTCUSDT.png"
    },
    {
      "symbol": "ETHUSDT",
      "base": "ETH",
      "quote": "USDT",
      "lastPrice": 2031.33,
      "priceChangePercent": 2.538,
      "quoteVolume": 1174164161.894045,
      "rankByQuoteVolume": 3,
      "tradeCount": 9242539,
      "highPrice": 2090,
      "lowPrice": 1907.41,
      "logoPath": "/data/logos/ETHUSDT.png"
    },
    {
      "symbol": "SOLUSDT",
      "base": "SOL",
      "quote": "USDT",
      "lastPrice": 87.46,
      "priceChangePercent": 3.699,
      "quoteVolume": 432518079.40372,
      "rankByQuoteVolume": 4,
      "tradeCount": 1983160,
      "highPrice": 90.29,
      "lowPrice": 81.69,
      "logoPath": "/data/logos/SOLUSDT.png"
    },
    {
      "symbol": "USD1USDT",
      "base": "USD1",
      "quote": "USDT",
      "lastPrice": 0.9995,
      "priceChangePercent": 0.02,
      "quoteVolume": 278452745.2785,
      "rankByQuoteVolume": 5,
      "tradeCount": 186897,
      "highPrice": 1.0003,
      "lowPrice": 0.9993,
      "logoPath": null
    },
    {
      "symbol": "XRPUSDT",
      "base": "XRP",
      "quote": "USDT",
      "lastPrice": 1.4004,
      "priceChangePercent": 2.182,
      "quoteVolume": 236955721.51388,
      "rankByQuoteVolume": 6,
      "tradeCount": 1159955,
      "highPrice": 1.423,
      "lowPrice": 1.3341,
      "logoPath": "/data/logos/XRPUSDT.png"
    },
    {
      "symbol": "PAXGUSDT",
      "base": "PAXG",
      "quote": "USDT",
      "lastPrice": 5317.65,
      "priceChangePercent": -1.57,
      "quoteVolume": 185398412.27364,
      "rankByQuoteVolume": 7,
      "tradeCount": 270741,
      "highPrice": 5459.65,
      "lowPrice": 5275.22,
      "logoPath": "/data/logos/PAXGUSDT.png"
    },
    {
      "symbol": "BNBUSDT",
      "base": "BNB",
      "quote": "USDT",
      "lastPrice": 641.75,
      "priceChangePercent": 2.972,
      "quoteVolume": 128740070.14395,
      "rankByQuoteVolume": 8,
      "tradeCount": 1374310,
      "highPrice": 652.87,
      "lowPrice": 610.89,
      "logoPath": "/data/logos/BNBUSDT.png"
    },
    {
      "symbol": "UUSDT",
      "base": "U",
      "quote": "USDT",
      "lastPrice": 0.9999,
      "priceChangePercent": 0.01,
      "quoteVolume": 122773956.2164,
      "rankByQuoteVolume": 9,
      "tradeCount": 10017,
      "highPrice": 1.0007,
      "lowPrice": 0.9997,
      "logoPath": null
    },
    {
      "symbol": "DOGEUSDT",
      "base": "DOGE",
      "quote": "USDT",
      "lastPrice": 0.09538,
      "priceChangePercent": 2.581,
      "quoteVolume": 90417842.87225,
      "rankByQuoteVolume": 10,
      "tradeCount": 1166116,
      "highPrice": 0.09771,
      "lowPrice": 0.09056,
      "logoPath": "/data/logos/DOGEUSDT.png"
    },
    {
      "symbol": "NEARUSDT",
      "base": "NEAR",
      "quote": "USDT",
      "lastPrice": 1.319,
      "priceChangePercent": 14.996,
      "quoteVolume": 62722032.7314,
      "rankByQuoteVolume": 11,
      "tradeCount": 366348,
      "highPrice": 1.341,
      "lowPrice": 1.112,
      "logoPath": null
    },
    {
      "symbol": "EURUSDT",
      "base": "EUR",
      "quote": "USDT",
      "lastPrice": 1.1686,
      "priceChangePercent": -0.958,
      "quoteVolume": 55878367.1992,
      "rankByQuoteVolume": 12,
      "tradeCount": 64810,
      "highPrice": 1.1801,
      "lowPrice": 1.1673,
      "logoPath": "/data/logos/EURUSDT.png"
    },
    {
      "symbol": "SUIUSDT",
      "base": "SUI",
      "quote": "USDT",
      "lastPrice": 0.94,
      "priceChangePercent": 5.075,
      "quoteVolume": 55810006.96134,
      "rankByQuoteVolume": 13,
      "tradeCount": 463749,
      "highPrice": 0.9676,
      "lowPrice": 0.8663,
      "logoPath": null
    },
    {
      "symbol": "PEPEUSDT",
      "base": "PEPE",
      "quote": "USDT",
      "lastPrice": 0.0000036,
      "priceChangePercent": 3.152,
      "quoteVolume": 48856838.71120016,
      "rankByQuoteVolume": 14,
      "tradeCount": 130051,
      "highPrice": 0.0000037,
      "lowPrice": 0.00000336,
      "logoPath": null
    },
    {
      "symbol": "FDUSDUSDT",
      "base": "FDUSD",
      "quote": "USDT",
      "lastPrice": 0.9997,
      "priceChangePercent": -0.08,
      "quoteVolume": 46547717.8901,
      "rankByQuoteVolume": 15,
      "tradeCount": 32113,
      "highPrice": 1.0013,
      "lowPrice": 0.9994,
      "logoPath": null
    },
    {
      "symbol": "ZECUSDT",
      "base": "ZEC",
      "quote": "USDT",
      "lastPrice": 219.99,
      "priceChangePercent": 0.475,
      "quoteVolume": 44171905.926,
      "rankByQuoteVolume": 16,
      "tradeCount": 220752,
      "highPrice": 226.28,
      "lowPrice": 211.29,
      "logoPath": "/data/logos/ZECUSDT.png"
    },
    {
      "symbol": "ADAUSDT",
      "base": "ADA",
      "quote": "USDT",
      "lastPrice": 0.2811,
      "priceChangePercent": 1.553,
      "quoteVolume": 43069415.9222,
      "rankByQuoteVolume": 17,
      "tradeCount": 226589,
      "highPrice": 0.2887,
      "lowPrice": 0.2685,
      "logoPath": "/data/logos/ADAUSDT.png"
    },
    {
      "symbol": "AVAXUSDT",
      "base": "AVAX",
      "quote": "USDT",
      "lastPrice": 9.25,
      "priceChangePercent": 1.985,
      "quoteVolume": 34409901.9338,
      "rankByQuoteVolume": 18,
      "tradeCount": 115581,
      "highPrice": 9.48,
      "lowPrice": 8.85,
      "logoPath": "/data/logos/AVAXUSDT.png"
    },
    {
      "symbol": "LINKUSDT",
      "base": "LINK",
      "quote": "USDT",
      "lastPrice": 9.05,
      "priceChangePercent": 2.26,
      "quoteVolume": 32455359.5915,
      "rankByQuoteVolume": 19,
      "tradeCount": 90645,
      "highPrice": 9.27,
      "lowPrice": 8.54,
      "logoPath": "/data/logos/LINKUSDT.png"
    },
    {
      "symbol": "TRXUSDT",
      "base": "TRX",
      "quote": "USDT",
      "lastPrice": 0.2825,
      "priceChangePercent": 0.355,
      "quoteVolume": 29390523.92615,
      "rankByQuoteVolume": 20,
      "tradeCount": 67274,
      "highPrice": 0.2832,
      "lowPrice": 0.2799,
      "logoPath": "/data/logos/TRXUSDT.png"
    },
    {
      "symbol": "LTCUSDT",
      "base": "LTC",
      "quote": "USDT",
      "lastPrice": 54.65,
      "priceChangePercent": 1.731,
      "quoteVolume": 24109375.52291,
      "rankByQuoteVolume": 21,
      "tradeCount": 285648,
      "highPrice": 55.72,
      "lowPrice": 52.47,
      "logoPath": "/data/logos/LTCUSDT.png"
    },
    {
      "symbol": "ENSOUSDT",
      "base": "ENSO",
      "quote": "USDT",
      "lastPrice": 1.407,
      "priceChangePercent": 5.236,
      "quoteVolume": 23724895.04486,
      "rankByQuoteVolume": 22,
      "tradeCount": 274315,
      "highPrice": 1.497,
      "lowPrice": 1.259,
      "logoPath": null
    },
    {
      "symbol": "DOTUSDT",
      "base": "DOT",
      "quote": "USDT",
      "lastPrice": 1.543,
      "priceChangePercent": 0.325,
      "quoteVolume": 22755636.72168,
      "rankByQuoteVolume": 23,
      "tradeCount": 121290,
      "highPrice": 1.603,
      "lowPrice": 1.498,
      "logoPath": "/data/logos/DOTUSDT.png"
    },
    {
      "symbol": "PUMPUSDT",
      "base": "PUMP",
      "quote": "USDT",
      "lastPrice": 0.002019,
      "priceChangePercent": 4.126,
      "quoteVolume": 21803794.258094,
      "rankByQuoteVolume": 24,
      "tradeCount": 149755,
      "highPrice": 0.002114,
      "lowPrice": 0.00183,
      "logoPath": null
    },
    {
      "symbol": "AAVEUSDT",
      "base": "AAVE",
      "quote": "USDT",
      "lastPrice": 124.53,
      "priceChangePercent": 8.855,
      "quoteVolume": 19509660.9972,
      "rankByQuoteVolume": 25,
      "tradeCount": 278481,
      "highPrice": 126.96,
      "lowPrice": 110.63,
      "logoPath": "/data/logos/AAVEUSDT.png"
    },
    {
      "symbol": "TAOUSDT",
      "base": "TAO",
      "quote": "USDT",
      "lastPrice": 187.6,
      "priceChangePercent": 4.922,
      "quoteVolume": 19392883.69811,
      "rankByQuoteVolume": 26,
      "tradeCount": 113175,
      "highPrice": 195.2,
      "lowPrice": 172.4,
      "logoPath": null
    },
    {
      "symbol": "KITEUSDT",
      "base": "KITE",
      "quote": "USDT",
      "lastPrice": 0.2363,
      "priceChangePercent": -8.8,
      "quoteVolume": 19306495.16231,
      "rankByQuoteVolume": 27,
      "tradeCount": 219054,
      "highPrice": 0.2597,
      "lowPrice": 0.2303,
      "logoPath": null
    },
    {
      "symbol": "ASTERUSDT",
      "base": "ASTER",
      "quote": "USDT",
      "lastPrice": 0.711,
      "priceChangePercent": 0,
      "quoteVolume": 19004082.33931,
      "rankByQuoteVolume": 28,
      "tradeCount": 58177,
      "highPrice": 0.724,
      "lowPrice": 0.69,
      "logoPath": null
    },
    {
      "symbol": "ENAUSDT",
      "base": "ENA",
      "quote": "USDT",
      "lastPrice": 0.1148,
      "priceChangePercent": 9.751,
      "quoteVolume": 17438691.39859,
      "rankByQuoteVolume": 29,
      "tradeCount": 80864,
      "highPrice": 0.1154,
      "lowPrice": 0.1008,
      "logoPath": null
    },
    {
      "symbol": "UNIUSDT",
      "base": "UNI",
      "quote": "USDT",
      "lastPrice": 3.92,
      "priceChangePercent": 3.869,
      "quoteVolume": 17153921.4025,
      "rankByQuoteVolume": 30,
      "tradeCount": 126068,
      "highPrice": 4.048,
      "lowPrice": 3.667,
      "logoPath": "/data/logos/UNIUSDT.png"
    },
    {
      "symbol": "BCHUSDT",
      "base": "BCH",
      "quote": "USDT",
      "lastPrice": 447.6,
      "priceChangePercent": 1.612,
      "quoteVolume": 15627546.1738,
      "rankByQuoteVolume": 31,
      "tradeCount": 119261,
      "highPrice": 454.4,
      "lowPrice": 432,
      "logoPath": "/data/logos/BCHUSDT.png"
    },
    {
      "symbol": "VIRTUALUSDT",
      "base": "VIRTUAL",
      "quote": "USDT",
      "lastPrice": 0.7868,
      "priceChangePercent": 13.046,
      "quoteVolume": 15196529.42154,
      "rankByQuoteVolume": 32,
      "tradeCount": 140336,
      "highPrice": 0.7902,
      "lowPrice": 0.6744,
      "logoPath": null
    },
    {
      "symbol": "WLDUSDT",
      "base": "WLD",
      "quote": "USDT",
      "lastPrice": 0.4132,
      "priceChangePercent": 6.687,
      "quoteVolume": 13754346.59146,
      "rankByQuoteVolume": 33,
      "tradeCount": 143151,
      "highPrice": 0.4183,
      "lowPrice": 0.3766,
      "logoPath": null
    },
    {
      "symbol": "PENGUUSDT",
      "base": "PENGU",
      "quote": "USDT",
      "lastPrice": 0.007241,
      "priceChangePercent": 7.115,
      "quoteVolume": 13748027.476549,
      "rankByQuoteVolume": 34,
      "tradeCount": 215612,
      "highPrice": 0.007642,
      "lowPrice": 0.006527,
      "logoPath": null
    },
    {
      "symbol": "SAHARAUSDT",
      "base": "SAHARA",
      "quote": "USDT",
      "lastPrice": 0.02491,
      "priceChangePercent": 6.181,
      "quoteVolume": 13587635.37181,
      "rankByQuoteVolume": 35,
      "tradeCount": 184059,
      "highPrice": 0.0292,
      "lowPrice": 0.02223,
      "logoPath": null
    },
    {
      "symbol": "FILUSDT",
      "base": "FIL",
      "quote": "USDT",
      "lastPrice": 0.998,
      "priceChangePercent": 2.781,
      "quoteVolume": 13416588.51082,
      "rankByQuoteVolume": 36,
      "tradeCount": 69699,
      "highPrice": 1.029,
      "lowPrice": 0.942,
      "logoPath": "/data/logos/FILUSDT.png"
    },
    {
      "symbol": "ARBUSDT",
      "base": "ARB",
      "quote": "USDT",
      "lastPrice": 0.1038,
      "priceChangePercent": 4.217,
      "quoteVolume": 12857645.70586,
      "rankByQuoteVolume": 37,
      "tradeCount": 49986,
      "highPrice": 0.1087,
      "lowPrice": 0.0958,
      "logoPath": null
    },
    {
      "symbol": "ESPUSDT",
      "base": "ESP",
      "quote": "USDT",
      "lastPrice": 0.12574,
      "priceChangePercent": -9.481,
      "quoteVolume": 12446901.46446,
      "rankByQuoteVolume": 38,
      "tradeCount": 153153,
      "highPrice": 0.14296,
      "lowPrice": 0.12111,
      "logoPath": null
    },
    {
      "symbol": "ZROUSDT",
      "base": "ZRO",
      "quote": "USDT",
      "lastPrice": 1.872,
      "priceChangePercent": 6.364,
      "quoteVolume": 12440234.76949,
      "rankByQuoteVolume": 39,
      "tradeCount": 130050,
      "highPrice": 1.935,
      "lowPrice": 1.713,
      "logoPath": null
    },
    {
      "symbol": "APTUSDT",
      "base": "APT",
      "quote": "USDT",
      "lastPrice": 0.965,
      "priceChangePercent": 3.43,
      "quoteVolume": 11919002.53541,
      "rankByQuoteVolume": 40,
      "tradeCount": 51769,
      "highPrice": 0.988,
      "lowPrice": 0.905,
      "logoPath": null
    },
    {
      "symbol": "HBARUSDT",
      "base": "HBAR",
      "quote": "USDT",
      "lastPrice": 0.10019,
      "priceChangePercent": 1.892,
      "quoteVolume": 11657879.94988,
      "rankByQuoteVolume": 41,
      "tradeCount": 180530,
      "highPrice": 0.10297,
      "lowPrice": 0.09568,
      "logoPath": null
    },
    {
      "symbol": "XPLUSDT",
      "base": "XPL",
      "quote": "USDT",
      "lastPrice": 0.1044,
      "priceChangePercent": 6.205,
      "quoteVolume": 11533572.21225,
      "rankByQuoteVolume": 42,
      "tradeCount": 146273,
      "highPrice": 0.1077,
      "lowPrice": 0.0947,
      "logoPath": null
    },
    {
      "symbol": "KAVAUSDT",
      "base": "KAVA",
      "quote": "USDT",
      "lastPrice": 0.0573,
      "priceChangePercent": 15.292,
      "quoteVolume": 11382068.57822,
      "rankByQuoteVolume": 43,
      "tradeCount": 73101,
      "highPrice": 0.0696,
      "lowPrice": 0.0476,
      "logoPath": null
    },
    {
      "symbol": "FORMUSDT",
      "base": "FORM",
      "quote": "USDT",
      "lastPrice": 0.2865,
      "priceChangePercent": 34.066,
      "quoteVolume": 11340083.99192,
      "rankByQuoteVolume": 44,
      "tradeCount": 116260,
      "highPrice": 0.2923,
      "lowPrice": 0.2057,
      "logoPath": null
    },
    {
      "symbol": "DASHUSDT",
      "base": "DASH",
      "quote": "USDT",
      "lastPrice": 34.73,
      "priceChangePercent": 7.757,
      "quoteVolume": 10608943.36919,
      "rankByQuoteVolume": 45,
      "tradeCount": 56449,
      "highPrice": 35.16,
      "lowPrice": 31.04,
      "logoPath": "/data/logos/DASHUSDT.png"
    },
    {
      "symbol": "WLFIUSDT",
      "base": "WLFI",
      "quote": "USDT",
      "lastPrice": 0.109,
      "priceChangePercent": 0.554,
      "quoteVolume": 10545866.34365,
      "rankByQuoteVolume": 46,
      "tradeCount": 72679,
      "highPrice": 0.111,
      "lowPrice": 0.1043,
      "logoPath": null
    },
    {
      "symbol": "SHIBUSDT",
      "base": "SHIB",
      "quote": "USDT",
      "lastPrice": 0.00000564,
      "priceChangePercent": 1.075,
      "quoteVolume": 10165901.0070919,
      "rankByQuoteVolume": 47,
      "tradeCount": 394810,
      "highPrice": 0.0000058,
      "lowPrice": 0.00000544,
      "logoPath": null
    },
    {
      "symbol": "ALICEUSDT",
      "base": "ALICE",
      "quote": "USDT",
      "lastPrice": 0.1462,
      "priceChangePercent": -6.041,
      "quoteVolume": 9664156.026717,
      "rankByQuoteVolume": 48,
      "tradeCount": 117030,
      "highPrice": 0.1774,
      "lowPrice": 0.1422,
      "logoPath": null
    },
    {
      "symbol": "WIFUSDT",
      "base": "WIF",
      "quote": "USDT",
      "lastPrice": 0.203,
      "priceChangePercent": 5.181,
      "quoteVolume": 9477745.92662,
      "rankByQuoteVolume": 49,
      "tradeCount": 42897,
      "highPrice": 0.211,
      "lowPrice": 0.185,
      "logoPath": null
    },
    {
      "symbol": "ICPUSDT",
      "base": "ICP",
      "quote": "USDT",
      "lastPrice": 2.434,
      "priceChangePercent": 0.87,
      "quoteVolume": 9278198.05279,
      "rankByQuoteVolume": 50,
      "tradeCount": 77526,
      "highPrice": 2.55,
      "lowPrice": 2.34,
      "logoPath": "/data/logos/ICPUSDT.png"
    },
    {
      "symbol": "TONUSDT",
      "base": "TON",
      "quote": "USDT",
      "lastPrice": 1.235,
      "priceChangePercent": 1.23,
      "quoteVolume": 9270639.06587,
      "rankByQuoteVolume": 51,
      "tradeCount": 66008,
      "highPrice": 1.256,
      "lowPrice": 1.187,
      "logoPath": null
    },
    {
      "symbol": "XLMUSDT",
      "base": "XLM",
      "quote": "USDT",
      "lastPrice": 0.1586,
      "priceChangePercent": 1.667,
      "quoteVolume": 8491889.4911,
      "rankByQuoteVolume": 52,
      "tradeCount": 122230,
      "highPrice": 0.1622,
      "lowPrice": 0.1518,
      "logoPath": "/data/logos/XLMUSDT.png"
    },
    {
      "symbol": "FIOUSDT",
      "base": "FIO",
      "quote": "USDT",
      "lastPrice": 0.01071,
      "priceChangePercent": -3.86,
      "quoteVolume": 8242956.40521,
      "rankByQuoteVolume": 53,
      "tradeCount": 59804,
      "highPrice": 0.0119,
      "lowPrice": 0.0096,
      "logoPath": null
    },
    {
      "symbol": "KNCUSDT",
      "base": "KNC",
      "quote": "USDT",
      "lastPrice": 0.1505,
      "priceChangePercent": 12.565,
      "quoteVolume": 7588775.72496,
      "rankByQuoteVolume": 54,
      "tradeCount": 69139,
      "highPrice": 0.1798,
      "lowPrice": 0.1299,
      "logoPath": "/data/logos/KNCUSDT.png"
    },
    {
      "symbol": "ZAMAUSDT",
      "base": "ZAMA",
      "quote": "USDT",
      "lastPrice": 0.01956,
      "priceChangePercent": -8.341,
      "quoteVolume": 7554030.61868,
      "rankByQuoteVolume": 55,
      "tradeCount": 69979,
      "highPrice": 0.02144,
      "lowPrice": 0.01921,
      "logoPath": null
    },
    {
      "symbol": "POLUSDT",
      "base": "POL",
      "quote": "USDT",
      "lastPrice": 0.102,
      "priceChangePercent": -3.409,
      "quoteVolume": 7331707.82531,
      "rankByQuoteVolume": 56,
      "tradeCount": 66786,
      "highPrice": 0.1088,
      "lowPrice": 0.101,
      "logoPath": null
    },
    {
      "symbol": "SEIUSDT",
      "base": "SEI",
      "quote": "USDT",
      "lastPrice": 0.0692,
      "priceChangePercent": 1.022,
      "quoteVolume": 6984189.32022,
      "rankByQuoteVolume": 57,
      "tradeCount": 67690,
      "highPrice": 0.0716,
      "lowPrice": 0.0666,
      "logoPath": null
    },
    {
      "symbol": "BONKUSDT",
      "base": "BONK",
      "quote": "USDT",
      "lastPrice": 0.00000612,
      "priceChangePercent": 3.729,
      "quoteVolume": 6916670.899809,
      "rankByQuoteVolume": 58,
      "tradeCount": 489999,
      "highPrice": 0.00000636,
      "lowPrice": 0.00000568,
      "logoPath": null
    },
    {
      "symbol": "TRUMPUSDT",
      "base": "TRUMP",
      "quote": "USDT",
      "lastPrice": 3.497,
      "priceChangePercent": 1.333,
      "quoteVolume": 6825784.144213,
      "rankByQuoteVolume": 59,
      "tradeCount": 100095,
      "highPrice": 3.569,
      "lowPrice": 3.343,
      "logoPath": null
    },
    {
      "symbol": "OPUSDT",
      "base": "OP",
      "quote": "USDT",
      "lastPrice": 0.127,
      "priceChangePercent": 3.928,
      "quoteVolume": 6719445.078683,
      "rankByQuoteVolume": 60,
      "tradeCount": 52763,
      "highPrice": 0.13,
      "lowPrice": 0.1184,
      "logoPath": null
    },
    {
      "symbol": "RLUSDUSDT",
      "base": "RLUSD",
      "quote": "USDT",
      "lastPrice": 0.9999,
      "priceChangePercent": -0.01,
      "quoteVolume": 6694394.6315,
      "rankByQuoteVolume": 61,
      "tradeCount": 9218,
      "highPrice": 1.0005,
      "lowPrice": 0.9998,
      "logoPath": null
    },
    {
      "symbol": "CRVUSDT",
      "base": "CRV",
      "quote": "USDT",
      "lastPrice": 0.2549,
      "priceChangePercent": 4.596,
      "quoteVolume": 6462861.53174,
      "rankByQuoteVolume": 62,
      "tradeCount": 61679,
      "highPrice": 0.2625,
      "lowPrice": 0.236,
      "logoPath": "/data/logos/CRVUSDT.png"
    },
    {
      "symbol": "BFUSDUSDT",
      "base": "BFUSD",
      "quote": "USDT",
      "lastPrice": 0.9992,
      "priceChangePercent": 0,
      "quoteVolume": 6395731.4338,
      "rankByQuoteVolume": 63,
      "tradeCount": 2200,
      "highPrice": 0.9996,
      "lowPrice": 0.999,
      "logoPath": null
    },
    {
      "symbol": "TLMUSDT",
      "base": "TLM",
      "quote": "USDT",
      "lastPrice": 0.001711,
      "priceChangePercent": 6.273,
      "quoteVolume": 6303555.864449,
      "rankByQuoteVolume": 64,
      "tradeCount": 83216,
      "highPrice": 0.002091,
      "lowPrice": 0.001581,
      "logoPath": null
    },
    {
      "symbol": "FETUSDT",
      "base": "FET",
      "quote": "USDT",
      "lastPrice": 0.1528,
      "priceChangePercent": 0.197,
      "quoteVolume": 5924070.52025,
      "rankByQuoteVolume": 65,
      "tradeCount": 60344,
      "highPrice": 0.1597,
      "lowPrice": 0.1465,
      "logoPath": null
    },
    {
      "symbol": "RENDERUSDT",
      "base": "RENDER",
      "quote": "USDT",
      "lastPrice": 1.382,
      "priceChangePercent": 1.993,
      "quoteVolume": 5541529.66227,
      "rankByQuoteVolume": 66,
      "tradeCount": 29053,
      "highPrice": 1.44,
      "lowPrice": 1.311,
      "logoPath": null
    },
    {
      "symbol": "ARUSDT",
      "base": "AR",
      "quote": "USDT",
      "lastPrice": 1.63,
      "priceChangePercent": 5.161,
      "quoteVolume": 5257993.2635,
      "rankByQuoteVolume": 67,
      "tradeCount": 16847,
      "highPrice": 1.69,
      "lowPrice": 1.5,
      "logoPath": null
    },
    {
      "symbol": "FLOKIUSDT",
      "base": "FLOKI",
      "quote": "USDT",
      "lastPrice": 0.0000287,
      "priceChangePercent": 4.023,
      "quoteVolume": 5106913.30655703,
      "rankByQuoteVolume": 68,
      "tradeCount": 1853933,
      "highPrice": 0.0000296,
      "lowPrice": 0.00002667,
      "logoPath": null
    },
    {
      "symbol": "XUSDUSDT",
      "base": "XUSD",
      "quote": "USDT",
      "lastPrice": 1.0001,
      "priceChangePercent": 0,
      "quoteVolume": 5101400.3049,
      "rankByQuoteVolume": 69,
      "tradeCount": 2187,
      "highPrice": 1.0007,
      "lowPrice": 1,
      "logoPath": null
    },
    {
      "symbol": "PHAUSDT",
      "base": "PHA",
      "quote": "USDT",
      "lastPrice": 0.0256,
      "priceChangePercent": 17.431,
      "quoteVolume": 5040624.8665,
      "rankByQuoteVolume": 70,
      "tradeCount": 43089,
      "highPrice": 0.0295,
      "lowPrice": 0.0212,
      "logoPath": null
    },
    {
      "symbol": "CAKEUSDT",
      "base": "CAKE",
      "quote": "USDT",
      "lastPrice": 1.354,
      "priceChangePercent": 3.044,
      "quoteVolume": 4959625.82565,
      "rankByQuoteVolume": 71,
      "tradeCount": 46358,
      "highPrice": 1.382,
      "lowPrice": 1.28,
      "logoPath": null
    },
    {
      "symbol": "BARDUSDT",
      "base": "BARD",
      "quote": "USDT",
      "lastPrice": 0.9944,
      "priceChangePercent": 0.121,
      "quoteVolume": 4743551.33868,
      "rankByQuoteVolume": 72,
      "tradeCount": 62796,
      "highPrice": 1.0155,
      "lowPrice": 0.99,
      "logoPath": null
    },
    {
      "symbol": "ONDOUSDT",
      "base": "ONDO",
      "quote": "USDT",
      "lastPrice": 0.2623,
      "priceChangePercent": 2.461,
      "quoteVolume": 4721443.0583,
      "rankByQuoteVolume": 73,
      "tradeCount": 56718,
      "highPrice": 0.2709,
      "lowPrice": 0.2475,
      "logoPath": null
    },
    {
      "symbol": "AIXBTUSDT",
      "base": "AIXBT",
      "quote": "USDT",
      "lastPrice": 0.0235,
      "priceChangePercent": 12.981,
      "quoteVolume": 4559121.78387,
      "rankByQuoteVolume": 74,
      "tradeCount": 32509,
      "highPrice": 0.0244,
      "lowPrice": 0.02,
      "logoPath": null
    },
    {
      "symbol": "MORPHOUSDT",
      "base": "MORPHO",
      "quote": "USDT",
      "lastPrice": 1.915,
      "priceChangePercent": 10.822,
      "quoteVolume": 4548188.71919,
      "rankByQuoteVolume": 75,
      "tradeCount": 61129,
      "highPrice": 1.961,
      "lowPrice": 1.674,
      "logoPath": null
    },
    {
      "symbol": "TIAUSDT",
      "base": "TIA",
      "quote": "USDT",
      "lastPrice": 0.3345,
      "priceChangePercent": 4.892,
      "quoteVolume": 4496732.075929,
      "rankByQuoteVolume": 76,
      "tradeCount": 76751,
      "highPrice": 0.3452,
      "lowPrice": 0.3076,
      "logoPath": null
    },
    {
      "symbol": "STRKUSDT",
      "base": "STRK",
      "quote": "USDT",
      "lastPrice": 0.0415,
      "priceChangePercent": 2.469,
      "quoteVolume": 4465455.494192,
      "rankByQuoteVolume": 77,
      "tradeCount": 9398,
      "highPrice": 0.0424,
      "lowPrice": 0.0392,
      "logoPath": null
    },
    {
      "symbol": "SUNUSDT",
      "base": "SUN",
      "quote": "USDT",
      "lastPrice": 0.01585,
      "priceChangePercent": 4.208,
      "quoteVolume": 4275535.78238,
      "rankByQuoteVolume": 78,
      "tradeCount": 63737,
      "highPrice": 0.01617,
      "lowPrice": 0.01506,
      "logoPath": null
    },
    {
      "symbol": "EIGENUSDT",
      "base": "EIGEN",
      "quote": "USDT",
      "lastPrice": 0.187,
      "priceChangePercent": 3.315,
      "quoteVolume": 4202339.04487,
      "rankByQuoteVolume": 79,
      "tradeCount": 24091,
      "highPrice": 0.191,
      "lowPrice": 0.173,
      "logoPath": null
    },
    {
      "symbol": "WBTCUSDT",
      "base": "WBTC",
      "quote": "USDT",
      "lastPrice": 68860.72,
      "priceChangePercent": 3.923,
      "quoteVolume": 4141608.7977474,
      "rankByQuoteVolume": 80,
      "tradeCount": 15131,
      "highPrice": 69900,
      "lowPrice": 64892.59,
      "logoPath": "/data/logos/WBTCUSDT.png"
    },
    {
      "symbol": "BREVUSDT",
      "base": "BREV",
      "quote": "USDT",
      "lastPrice": 0.1403,
      "priceChangePercent": 7.427,
      "quoteVolume": 4117404.50624,
      "rankByQuoteVolume": 81,
      "tradeCount": 36948,
      "highPrice": 0.1471,
      "lowPrice": 0.1271,
      "logoPath": null
    },
    {
      "symbol": "BIOUSDT",
      "base": "BIO",
      "quote": "USDT",
      "lastPrice": 0.0208,
      "priceChangePercent": 0.971,
      "quoteVolume": 4088484.00775,
      "rankByQuoteVolume": 82,
      "tradeCount": 13150,
      "highPrice": 0.0213,
      "lowPrice": 0.0199,
      "logoPath": null
    },
    {
      "symbol": "DENTUSDT",
      "base": "DENT",
      "quote": "USDT",
      "lastPrice": 0.000301,
      "priceChangePercent": -5.938,
      "quoteVolume": 3980591.678031,
      "rankByQuoteVolume": 83,
      "tradeCount": 21554,
      "highPrice": 0.000339,
      "lowPrice": 0.000282,
      "logoPath": "/data/logos/DENTUSDT.png"
    },
    {
      "symbol": "ATUSDT",
      "base": "AT",
      "quote": "USDT",
      "lastPrice": 0.1592,
      "priceChangePercent": 6.917,
      "quoteVolume": 3746360.32503,
      "rankByQuoteVolume": 84,
      "tradeCount": 91088,
      "highPrice": 0.161,
      "lowPrice": 0.134,
      "logoPath": null
    },
    {
      "symbol": "INJUSDT",
      "base": "INJ",
      "quote": "USDT",
      "lastPrice": 3.129,
      "priceChangePercent": 3.165,
      "quoteVolume": 3696380.80937,
      "rankByQuoteVolume": 85,
      "tradeCount": 41613,
      "highPrice": 3.156,
      "lowPrice": 2.943,
      "logoPath": null
    },
    {
      "symbol": "DYDXUSDT",
      "base": "DYDX",
      "quote": "USDT",
      "lastPrice": 0.0977,
      "priceChangePercent": 6.196,
      "quoteVolume": 3692673.914466,
      "rankByQuoteVolume": 86,
      "tradeCount": 16339,
      "highPrice": 0.1036,
      "lowPrice": 0.0882,
      "logoPath": null
    },
    {
      "symbol": "ATOMUSDT",
      "base": "ATOM",
      "quote": "USDT",
      "lastPrice": 1.86,
      "priceChangePercent": 3.161,
      "quoteVolume": 3686127.15434,
      "rankByQuoteVolume": 87,
      "tradeCount": 26822,
      "highPrice": 1.881,
      "lowPrice": 1.763,
      "logoPath": "/data/logos/ATOMUSDT.png"
    },
    {
      "symbol": "IMXUSDT",
      "base": "IMX",
      "quote": "USDT",
      "lastPrice": 0.1671,
      "priceChangePercent": 3.532,
      "quoteVolume": 3505296.361491,
      "rankByQuoteVolume": 88,
      "tradeCount": 34502,
      "highPrice": 0.1811,
      "lowPrice": 0.156,
      "logoPath": null
    },
    {
      "symbol": "LDOUSDT",
      "base": "LDO",
      "quote": "USDT",
      "lastPrice": 0.3112,
      "priceChangePercent": 2.978,
      "quoteVolume": 3492521.176539,
      "rankByQuoteVolume": 89,
      "tradeCount": 54209,
      "highPrice": 0.3204,
      "lowPrice": 0.2933,
      "logoPath": null
    },
    {
      "symbol": "MIRAUSDT",
      "base": "MIRA",
      "quote": "USDT",
      "lastPrice": 0.0947,
      "priceChangePercent": 0.638,
      "quoteVolume": 3448751.20334,
      "rankByQuoteVolume": 90,
      "tradeCount": 25173,
      "highPrice": 0.0985,
      "lowPrice": 0.0898,
      "logoPath": null
    },
    {
      "symbol": "LUNCUSDT",
      "base": "LUNC",
      "quote": "USDT",
      "lastPrice": 0.00004286,
      "priceChangePercent": -1.335,
      "quoteVolume": 3426776.23021006,
      "rankByQuoteVolume": 91,
      "tradeCount": 46661,
      "highPrice": 0.00004398,
      "lowPrice": 0.000042,
      "logoPath": null
    },
    {
      "symbol": "ETHFIUSDT",
      "base": "ETHFI",
      "quote": "USDT",
      "lastPrice": 0.511,
      "priceChangePercent": 2.2,
      "quoteVolume": 3408629.6489,
      "rankByQuoteVolume": 92,
      "tradeCount": 26484,
      "highPrice": 0.524,
      "lowPrice": 0.485,
      "logoPath": null
    },
    {
      "symbol": "CHZUSDT",
      "base": "CHZ",
      "quote": "USDT",
      "lastPrice": 0.03503,
      "priceChangePercent": 5.037,
      "quoteVolume": 3388002.87684,
      "rankByQuoteVolume": 93,
      "tradeCount": 35383,
      "highPrice": 0.03546,
      "lowPrice": 0.03256,
      "logoPath": "/data/logos/CHZUSDT.png"
    },
    {
      "symbol": "EURIUSDT",
      "base": "EURI",
      "quote": "USDT",
      "lastPrice": 1.1686,
      "priceChangePercent": -0.924,
      "quoteVolume": 3284168.68907,
      "rankByQuoteVolume": 94,
      "tradeCount": 16537,
      "highPrice": 1.18,
      "lowPrice": 1.1661,
      "logoPath": null
    },
    {
      "symbol": "YGGUSDT",
      "base": "YGG",
      "quote": "USDT",
      "lastPrice": 0.0401,
      "priceChangePercent": 4.974,
      "quoteVolume": 3200547.63525,
      "rankByQuoteVolume": 95,
      "tradeCount": 15096,
      "highPrice": 0.0434,
      "lowPrice": 0.0369,
      "logoPath": null
    },
    {
      "symbol": "NEIROUSDT",
      "base": "NEIRO",
      "quote": "USDT",
      "lastPrice": 0.00006969,
      "priceChangePercent": 3.736,
      "quoteVolume": 3167539.91956228,
      "rankByQuoteVolume": 96,
      "tradeCount": 131293,
      "highPrice": 0.00007198,
      "lowPrice": 0.00006454,
      "logoPath": null
    },
    {
      "symbol": "ARKMUSDT",
      "base": "ARKM",
      "quote": "USDT",
      "lastPrice": 0.11,
      "priceChangePercent": 2.804,
      "quoteVolume": 3151123.0821,
      "rankByQuoteVolume": 97,
      "tradeCount": 14348,
      "highPrice": 0.113,
      "lowPrice": 0.102,
      "logoPath": null
    },
    {
      "symbol": "ETCUSDT",
      "base": "ETC",
      "quote": "USDT",
      "lastPrice": 8.83,
      "priceChangePercent": 3.275,
      "quoteVolume": 3139185.6378,
      "rankByQuoteVolume": 98,
      "tradeCount": 45925,
      "highPrice": 8.97,
      "lowPrice": 8.31,
      "logoPath": "/data/logos/ETCUSDT.png"
    },
    {
      "symbol": "ACEUSDT",
      "base": "ACE",
      "quote": "USDT",
      "lastPrice": 0.158,
      "priceChangePercent": 5.333,
      "quoteVolume": 3042930.1277,
      "rankByQuoteVolume": 99,
      "tradeCount": 20879,
      "highPrice": 0.169,
      "lowPrice": 0.146,
      "logoPath": null
    },
    {
      "symbol": "ALGOUSDT",
      "base": "ALGO",
      "quote": "USDT",
      "lastPrice": 0.0888,
      "priceChangePercent": 3.016,
      "quoteVolume": 3020154.1457,
      "rankByQuoteVolume": 100,
      "tradeCount": 14717,
      "highPrice": 0.0902,
      "lowPrice": 0.084,
      "logoPath": "/data/logos/ALGOUSDT.png"
    },
    {
      "symbol": "SENTUSDT",
      "base": "SENT",
      "quote": "USDT",
      "lastPrice": 0.02134,
      "priceChangePercent": 0.708,
      "quoteVolume": 2945220.87713,
      "rankByQuoteVolume": 101,
      "tradeCount": 30260,
      "highPrice": 0.02233,
      "lowPrice": 0.02063,
      "logoPath": null
    },
    {
      "symbol": "APEUSDT",
      "base": "APE",
      "quote": "USDT",
      "lastPrice": 0.1069,
      "priceChangePercent": 5.113,
      "quoteVolume": 2895484.344949,
      "rankByQuoteVolume": 102,
      "tradeCount": 27179,
      "highPrice": 0.1093,
      "lowPrice": 0.0979,
      "logoPath": "/data/logos/APEUSDT.png"
    },
    {
      "symbol": "VETUSDT",
      "base": "VET",
      "quote": "USDT",
      "lastPrice": 0.00738,
      "priceChangePercent": 2.786,
      "quoteVolume": 2893817.309072,
      "rankByQuoteVolume": 103,
      "tradeCount": 16970,
      "highPrice": 0.00749,
      "lowPrice": 0.00698,
      "logoPath": "/data/logos/VETUSDT.png"
    },
    {
      "symbol": "GIGGLEUSDT",
      "base": "GIGGLE",
      "quote": "USDT",
      "lastPrice": 26.84,
      "priceChangePercent": 2.599,
      "quoteVolume": 2870352.33647,
      "rankByQuoteVolume": 104,
      "tradeCount": 32486,
      "highPrice": 27.27,
      "lowPrice": 24.94,
      "logoPath": null
    },
    {
      "symbol": "WUSDT",
      "base": "W",
      "quote": "USDT",
      "lastPrice": 0.0194,
      "priceChangePercent": 4.865,
      "quoteVolume": 2802048.73611,
      "rankByQuoteVolume": 105,
      "tradeCount": 15742,
      "highPrice": 0.0198,
      "lowPrice": 0.0178,
      "logoPath": null
    },
    {
      "symbol": "PENDLEUSDT",
      "base": "PENDLE",
      "quote": "USDT",
      "lastPrice": 1.317,
      "priceChangePercent": 3.456,
      "quoteVolume": 2775285.1064,
      "rankByQuoteVolume": 106,
      "tradeCount": 29889,
      "highPrice": 1.356,
      "lowPrice": 1.234,
      "logoPath": null
    },
    {
      "symbol": "LINEAUSDT",
      "base": "LINEA",
      "quote": "USDT",
      "lastPrice": 0.00324,
      "priceChangePercent": 5.537,
      "quoteVolume": 2769885.11616,
      "rankByQuoteVolume": 107,
      "tradeCount": 27117,
      "highPrice": 0.00332,
      "lowPrice": 0.00295,
      "logoPath": null
    },
    {
      "symbol": "SIGNUSDT",
      "base": "SIGN",
      "quote": "USDT",
      "lastPrice": 0.02678,
      "priceChangePercent": 0.45,
      "quoteVolume": 2636526.83681,
      "rankByQuoteVolume": 108,
      "tradeCount": 57775,
      "highPrice": 0.0269,
      "lowPrice": 0.02516,
      "logoPath": null
    },
    {
      "symbol": "AXSUSDT",
      "base": "AXS",
      "quote": "USDT",
      "lastPrice": 1.29,
      "priceChangePercent": 0.467,
      "quoteVolume": 2632391.17303,
      "rankByQuoteVolume": 109,
      "tradeCount": 14810,
      "highPrice": 1.319,
      "lowPrice": 1.233,
      "logoPath": null
    },
    {
      "symbol": "OGUSDT",
      "base": "OG",
      "quote": "USDT",
      "lastPrice": 2.849,
      "priceChangePercent": 0.993,
      "quoteVolume": 2622348.383,
      "rankByQuoteVolume": 110,
      "tradeCount": 40324,
      "highPrice": 2.892,
      "lowPrice": 2.683,
      "logoPath": null
    },
    {
      "symbol": "1000SATSUSDT",
      "base": "1000SATS",
      "quote": "USDT",
      "lastPrice": 0.00001151,
      "priceChangePercent": 3.321,
      "quoteVolume": 2587744.74155763,
      "rankByQuoteVolume": 111,
      "tradeCount": 19701,
      "highPrice": 0.0000122,
      "lowPrice": 0.00001067,
      "logoPath": null
    },
    {
      "symbol": "ZENUSDT",
      "base": "ZEN",
      "quote": "USDT",
      "lastPrice": 5.602,
      "priceChangePercent": 5.281,
      "quoteVolume": 2536504.08773,
      "rankByQuoteVolume": 112,
      "tradeCount": 31810,
      "highPrice": 5.693,
      "lowPrice": 5.148,
      "logoPath": "/data/logos/ZENUSDT.png"
    },
    {
      "symbol": "PROVEUSDT",
      "base": "PROVE",
      "quote": "USDT",
      "lastPrice": 0.3062,
      "priceChangePercent": 5.441,
      "quoteVolume": 2516527.67021,
      "rankByQuoteVolume": 113,
      "tradeCount": 28342,
      "highPrice": 0.3187,
      "lowPrice": 0.2831,
      "logoPath": null
    },
    {
      "symbol": "USDEUSDT",
      "base": "USDE",
      "quote": "USDT",
      "lastPrice": 0.9991,
      "priceChangePercent": -0.02,
      "quoteVolume": 2477472.4704,
      "rankByQuoteVolume": 114,
      "tradeCount": 937,
      "highPrice": 0.9994,
      "lowPrice": 0.9991,
      "logoPath": null
    },
    {
      "symbol": "SKYUSDT",
      "base": "SKY",
      "quote": "USDT",
      "lastPrice": 0.07137,
      "priceChangePercent": 6.19,
      "quoteVolume": 2472228.22329,
      "rankByQuoteVolume": 115,
      "tradeCount": 38013,
      "highPrice": 0.07223,
      "lowPrice": 0.06605,
      "logoPath": "/data/logos/SKYUSDT.png"
    },
    {
      "symbol": "0GUSDT",
      "base": "0G",
      "quote": "USDT",
      "lastPrice": 0.63,
      "priceChangePercent": 0,
      "quoteVolume": 2408489.9742,
      "rankByQuoteVolume": 116,
      "tradeCount": 10864,
      "highPrice": 0.634,
      "lowPrice": 0.606,
      "logoPath": null
    },
    {
      "symbol": "MBOXUSDT",
      "base": "MBOX",
      "quote": "USDT",
      "lastPrice": 0.0187,
      "priceChangePercent": 0.538,
      "quoteVolume": 2399185.99693,
      "rankByQuoteVolume": 117,
      "tradeCount": 20255,
      "highPrice": 0.0208,
      "lowPrice": 0.0181,
      "logoPath": null
    },
    {
      "symbol": "GALAUSDT",
      "base": "GALA",
      "quote": "USDT",
      "lastPrice": 0.00361,
      "priceChangePercent": 2.266,
      "quoteVolume": 2254693.15403,
      "rankByQuoteVolume": 118,
      "tradeCount": 23811,
      "highPrice": 0.00371,
      "lowPrice": 0.0034,
      "logoPath": null
    },
    {
      "symbol": "NEWTUSDT",
      "base": "NEWT",
      "quote": "USDT",
      "lastPrice": 0.0723,
      "priceChangePercent": -2.165,
      "quoteVolume": 2236480.43515,
      "rankByQuoteVolume": 119,
      "tradeCount": 14173,
      "highPrice": 0.0763,
      "lowPrice": 0.0691,
      "logoPath": null
    },
    {
      "symbol": "ROSEUSDT",
      "base": "ROSE",
      "quote": "USDT",
      "lastPrice": 0.01177,
      "priceChangePercent": 4.622,
      "quoteVolume": 2154420.110886,
      "rankByQuoteVolume": 120,
      "tradeCount": 11491,
      "highPrice": 0.01185,
      "lowPrice": 0.01086,
      "logoPath": null
    },
    {
      "symbol": "BANANAS31USDT",
      "base": "BANANAS31",
      "quote": "USDT",
      "lastPrice": 0.00499,
      "priceChangePercent": 3.527,
      "quoteVolume": 2146292.118061,
      "rankByQuoteVolume": 121,
      "tradeCount": 40356,
      "highPrice": 0.00514,
      "lowPrice": 0.004682,
      "logoPath": null
    },
    {
      "symbol": "ZKUSDT",
      "base": "ZK",
      "quote": "USDT",
      "lastPrice": 0.01907,
      "priceChangePercent": 2.033,
      "quoteVolume": 2106174.531857,
      "rankByQuoteVolume": 122,
      "tradeCount": 23828,
      "highPrice": 0.01939,
      "lowPrice": 0.01809,
      "logoPath": null
    },
    {
      "symbol": "PNUTUSDT",
      "base": "PNUT",
      "quote": "USDT",
      "lastPrice": 0.0461,
      "priceChangePercent": 4.773,
      "quoteVolume": 2097194.85536,
      "rankByQuoteVolume": 123,
      "tradeCount": 25094,
      "highPrice": 0.0473,
      "lowPrice": 0.0423,
      "logoPath": null
    },
    {
      "symbol": "USUALUSDT",
      "base": "USUAL",
      "quote": "USDT",
      "lastPrice": 0.01385,
      "priceChangePercent": 14.368,
      "quoteVolume": 2085741.6996,
      "rankByQuoteVolume": 124,
      "tradeCount": 21760,
      "highPrice": 0.01407,
      "lowPrice": 0.01172,
      "logoPath": null
    },
    {
      "symbol": "ORDIUSDT",
      "base": "ORDI",
      "quote": "USDT",
      "lastPrice": 2.498,
      "priceChangePercent": 3.997,
      "quoteVolume": 2083722.80449,
      "rankByQuoteVolume": 125,
      "tradeCount": 31093,
      "highPrice": 2.578,
      "lowPrice": 2.314,
      "logoPath": null
    },
    {
      "symbol": "WBETHUSDT",
      "base": "WBETH",
      "quote": "USDT",
      "lastPrice": 2216.91,
      "priceChangePercent": 2.7,
      "quoteVolume": 2060299.875798,
      "rankByQuoteVolume": 126,
      "tradeCount": 7408,
      "highPrice": 2275,
      "lowPrice": 2079.02,
      "logoPath": null
    },
    {
      "symbol": "TRUUSDT",
      "base": "TRU",
      "quote": "USDT",
      "lastPrice": 0.0057,
      "priceChangePercent": 23.913,
      "quoteVolume": 2054619.5921,
      "rankByQuoteVolume": 127,
      "tradeCount": 16701,
      "highPrice": 0.0065,
      "lowPrice": 0.0045,
      "logoPath": null
    },
    {
      "symbol": "SUSDT",
      "base": "S",
      "quote": "USDT",
      "lastPrice": 0.04101,
      "priceChangePercent": 3.17,
      "quoteVolume": 2043165.554085,
      "rankByQuoteVolume": 128,
      "tradeCount": 56579,
      "highPrice": 0.04214,
      "lowPrice": 0.03825,
      "logoPath": null
    },
    {
      "symbol": "RUNEUSDT",
      "base": "RUNE",
      "quote": "USDT",
      "lastPrice": 0.409,
      "priceChangePercent": 3.023,
      "quoteVolume": 2014934.9172,
      "rankByQuoteVolume": 129,
      "tradeCount": 13326,
      "highPrice": 0.416,
      "lowPrice": 0.388,
      "logoPath": null
    },
    {
      "symbol": "DCRUSDT",
      "base": "DCR",
      "quote": "USDT",
      "lastPrice": 30.84,
      "priceChangePercent": 3.386,
      "quoteVolume": 1961413.24093,
      "rankByQuoteVolume": 130,
      "tradeCount": 25810,
      "highPrice": 31.46,
      "lowPrice": 27.81,
      "logoPath": "/data/logos/DCRUSDT.png"
    },
    {
      "symbol": "BERAUSDT",
      "base": "BERA",
      "quote": "USDT",
      "lastPrice": 0.613,
      "priceChangePercent": 1.658,
      "quoteVolume": 1892043.174804,
      "rankByQuoteVolume": 131,
      "tradeCount": 14055,
      "highPrice": 0.621,
      "lowPrice": 0.584,
      "logoPath": null
    },
    {
      "symbol": "TWTUSDT",
      "base": "TWT",
      "quote": "USDT",
      "lastPrice": 0.493,
      "priceChangePercent": 0.081,
      "quoteVolume": 1804594.3984,
      "rankByQuoteVolume": 132,
      "tradeCount": 26116,
      "highPrice": 0.5064,
      "lowPrice": 0.475,
      "logoPath": null
    },
    {
      "symbol": "CYBERUSDT",
      "base": "CYBER",
      "quote": "USDT",
      "lastPrice": 0.56,
      "priceChangePercent": 3.896,
      "quoteVolume": 1792917.48065,
      "rankByQuoteVolume": 133,
      "tradeCount": 10057,
      "highPrice": 0.573,
      "lowPrice": 0.52,
      "logoPath": null
    },
    {
      "symbol": "UMAUSDT",
      "base": "UMA",
      "quote": "USDT",
      "lastPrice": 0.438,
      "priceChangePercent": 5.288,
      "quoteVolume": 1767207.94,
      "rankByQuoteVolume": 134,
      "tradeCount": 14379,
      "highPrice": 0.49,
      "lowPrice": 0.407,
      "logoPath": "/data/logos/UMAUSDT.png"
    },
    {
      "symbol": "COSUSDT",
      "base": "COS",
      "quote": "USDT",
      "lastPrice": 0.00108,
      "priceChangePercent": -1.996,
      "quoteVolume": 1758156.7746003,
      "rankByQuoteVolume": 135,
      "tradeCount": 15767,
      "highPrice": 0.001141,
      "lowPrice": 0.001032,
      "logoPath": null
    },
    {
      "symbol": "STEEMUSDT",
      "base": "STEEM",
      "quote": "USDT",
      "lastPrice": 0.0619,
      "priceChangePercent": -0.642,
      "quoteVolume": 1751936.95799,
      "rankByQuoteVolume": 136,
      "tradeCount": 12944,
      "highPrice": 0.0681,
      "lowPrice": 0.0591,
      "logoPath": "/data/logos/STEEMUSDT.png"
    },
    {
      "symbol": "SOMIUSDT",
      "base": "SOMI",
      "quote": "USDT",
      "lastPrice": 0.194,
      "priceChangePercent": -2.168,
      "quoteVolume": 1721931.33834,
      "rankByQuoteVolume": 137,
      "tradeCount": 19065,
      "highPrice": 0.1988,
      "lowPrice": 0.1857,
      "logoPath": null
    },
    {
      "symbol": "FOGOUSDT",
      "base": "FOGO",
      "quote": "USDT",
      "lastPrice": 0.02525,
      "priceChangePercent": -1.483,
      "quoteVolume": 1718113.18762,
      "rankByQuoteVolume": 138,
      "tradeCount": 17524,
      "highPrice": 0.02646,
      "lowPrice": 0.02461,
      "logoPath": null
    },
    {
      "symbol": "MUBARAKUSDT",
      "base": "MUBARAK",
      "quote": "USDT",
      "lastPrice": 0.01397,
      "priceChangePercent": 3.943,
      "quoteVolume": 1708070.08894,
      "rankByQuoteVolume": 139,
      "tradeCount": 21675,
      "highPrice": 0.01436,
      "lowPrice": 0.01289,
      "logoPath": null
    },
    {
      "symbol": "INITUSDT",
      "base": "INIT",
      "quote": "USDT",
      "lastPrice": 0.0797,
      "priceChangePercent": 5.984,
      "quoteVolume": 1661413.87898,
      "rankByQuoteVolume": 140,
      "tradeCount": 12756,
      "highPrice": 0.0833,
      "lowPrice": 0.0737,
      "logoPath": null
    },
    {
      "symbol": "ALLOUSDT",
      "base": "ALLO",
      "quote": "USDT",
      "lastPrice": 0.1105,
      "priceChangePercent": 1.098,
      "quoteVolume": 1640261.53053,
      "rankByQuoteVolume": 141,
      "tradeCount": 16618,
      "highPrice": 0.115,
      "lowPrice": 0.1036,
      "logoPath": null
    },
    {
      "symbol": "RAYUSDT",
      "base": "RAY",
      "quote": "USDT",
      "lastPrice": 0.608,
      "priceChangePercent": 2.53,
      "quoteVolume": 1621329.9381,
      "rankByQuoteVolume": 142,
      "tradeCount": 8896,
      "highPrice": 0.631,
      "lowPrice": 0.574,
      "logoPath": "/data/logos/RAYUSDT.png"
    },
    {
      "symbol": "EULUSDT",
      "base": "EUL",
      "quote": "USDT",
      "lastPrice": 1.039,
      "priceChangePercent": -5.114,
      "quoteVolume": 1619689.94361,
      "rankByQuoteVolume": 143,
      "tradeCount": 16554,
      "highPrice": 1.095,
      "lowPrice": 0.998,
      "logoPath": null
    },
    {
      "symbol": "JASMYUSDT",
      "base": "JASMY",
      "quote": "USDT",
      "lastPrice": 0.00546,
      "priceChangePercent": 0.368,
      "quoteVolume": 1519777.129453,
      "rankByQuoteVolume": 144,
      "tradeCount": 7889,
      "highPrice": 0.00558,
      "lowPrice": 0.00516,
      "logoPath": null
    },
    {
      "symbol": "CFXUSDT",
      "base": "CFX",
      "quote": "USDT",
      "lastPrice": 0.0495,
      "priceChangePercent": 3.774,
      "quoteVolume": 1487196.9301,
      "rankByQuoteVolume": 145,
      "tradeCount": 12013,
      "highPrice": 0.051,
      "lowPrice": 0.0459,
      "logoPath": null
    },
    {
      "symbol": "LAYERUSDT",
      "base": "LAYER",
      "quote": "USDT",
      "lastPrice": 0.0906,
      "priceChangePercent": -3.514,
      "quoteVolume": 1479504.097335,
      "rankByQuoteVolume": 146,
      "tradeCount": 17995,
      "highPrice": 0.0952,
      "lowPrice": 0.0868,
      "logoPath": null
    },
    {
      "symbol": "SANTOSUSDT",
      "base": "SANTOS",
      "quote": "USDT",
      "lastPrice": 1.3,
      "priceChangePercent": 3.586,
      "quoteVolume": 1471827.58537,
      "rankByQuoteVolume": 147,
      "tradeCount": 11175,
      "highPrice": 1.355,
      "lowPrice": 1.221,
      "logoPath": null
    },
    {
      "symbol": "NEOUSDT",
      "base": "NEO",
      "quote": "USDT",
      "lastPrice": 2.68,
      "priceChangePercent": 2.018,
      "quoteVolume": 1470136.01114,
      "rankByQuoteVolume": 148,
      "tradeCount": 14177,
      "highPrice": 2.738,
      "lowPrice": 2.546,
      "logoPath": "/data/logos/NEOUSDT.png"
    },
    {
      "symbol": "DUSKUSDT",
      "base": "DUSK",
      "quote": "USDT",
      "lastPrice": 0.0841,
      "priceChangePercent": 4.602,
      "quoteVolume": 1454780.4299,
      "rankByQuoteVolume": 149,
      "tradeCount": 11240,
      "highPrice": 0.086,
      "lowPrice": 0.0786,
      "logoPath": null
    },
    {
      "symbol": "FFUSDT",
      "base": "FF",
      "quote": "USDT",
      "lastPrice": 0.07954,
      "priceChangePercent": 1.093,
      "quoteVolume": 1452110.634177,
      "rankByQuoteVolume": 150,
      "tradeCount": 21533,
      "highPrice": 0.07995,
      "lowPrice": 0.07719,
      "logoPath": null
    }
  ]
}
